COPYING
MANIFEST.in
README.rst
bootstrap.py
buildout.cfg
setup.py
docs/conf.py
docs/index.rst
docs/roc.png
xbob/__init__.py
xbob.paper.jmlr2013.egg-info/PKG-INFO
xbob.paper.jmlr2013.egg-info/SOURCES.txt
xbob.paper.jmlr2013.egg-info/dependency_links.txt
xbob.paper.jmlr2013.egg-info/entry_points.txt
xbob.paper.jmlr2013.egg-info/namespace_packages.txt
xbob.paper.jmlr2013.egg-info/requires.txt
xbob.paper.jmlr2013.egg-info/top_level.txt
xbob/paper/__init__.py
xbob/paper/jmlr2013/__init__.py
xbob/paper/jmlr2013/test.py
xbob/paper/jmlr2013/utils.py
xbob/paper/jmlr2013/scripts/__init__.py
xbob/paper/jmlr2013/scripts/evaluate.py
xbob/paper/jmlr2013/scripts/lbfgs_training.py
xbob/paper/jmlr2013/scripts/plot.py
xbob/paper/jmlr2013/scripts/rprop_training.py