Metadata-Version: 1.1
Name: xbob.paper.jmlr2013
Version: 0.2.0
Summary: Example of an article using Bob for reproducible experiments
Home-page: http://github.com/bioidiap/xbob.paper.jmlr2013
Author: Laurent El Shafey
Author-email: laurent.el-shafey@idiap.ch
License: GPLv3
Platform: UNKNOWN
Classifier: Development Status :: 4 - Beta
Classifier: Intended Audience :: Developers
Classifier: License :: OSI Approved :: GNU General Public License v3 (GPLv3)
Classifier: Natural Language :: English
Classifier: Programming Language :: Python
Classifier: Topic :: Scientific/Engineering :: Artificial Intelligence
